[
    {
        "user": "1310446718",
        "date": 1,
        "wordID": 0
    },
    {
        "user": "1280797395",
        "date": "10",
        "wordID": 20
    },
    {
        "user": "1932535957",
        "date": "10",
        "wordID": 20
    },
    {
        "user": "3167726334",
        "date": "16",
        "wordID": 20
    },
    {
        "user": "1178083220",
        "date": "16",
        "wordID": 20
    },
    {
        "user": "2962261096",
        "date": "16",
        "wordID": 20
    },
    {
        "user": "1179609029",
        "date": "17",
        "wordID": 20
    },
    {
        "user": "2544648791",
        "date": "17",
        "wordID": 20
    }
]